mlx_omni_server/__init__.py
mlx_omni_server/main.py
mlx_omni_server/routers.py
mlx_omni_server/chat/__init__.py
mlx_omni_server/chat/router.py
mlx_omni_server/chat/schema.py
mlx_omni_server/chat/text_models.py
mlx_omni_server/chat/mlx/__init__.py
mlx_omni_server/chat/mlx/mlx_model.py
mlx_omni_server/chat/mlx/models.py
mlx_omni_server/chat/mlx/outlines_logits_processor.py
mlx_omni_server/chat/mlx/prompt_cache.py
mlx_omni_server/chat/mlx/stop_tokens_checker.py
mlx_omni_server/chat/mlx/tools/__init__.py
mlx_omni_server/chat/mlx/tools/chat_tokenizer.py
mlx_omni_server/chat/mlx/tools/hugging_face.py
mlx_omni_server/chat/mlx/tools/llama3.py
mlx_omni_server/chat/mlx/tools/mistral.py
mlx_omni_server/chat/mlx/tools/utils.py
mlx_omni_server/chat/models/__init__.py
mlx_omni_server/chat/models/models.py
mlx_omni_server/chat/models/models_service.py
mlx_omni_server/chat/models/schema.py
mlx_omni_server/images/__init__.py
mlx_omni_server/images/images.py
mlx_omni_server/images/images_service.py
mlx_omni_server/images/schema.py
mlx_omni_server/middleware/logging.py
mlx_omni_server/stt/__init__.py
mlx_omni_server/stt/schema.py
mlx_omni_server/stt/stt.py
mlx_omni_server/stt/whisper_model.py
mlx_omni_server/tts/__init__.py
mlx_omni_server/tts/schema.py
mlx_omni_server/tts/tts.py
mlx_omni_server/tts/tts_service.py
mlx_omni_server/utils/logger.py
mxlengine-0.3.5.dist-info/METADATA
mxlengine-0.3.5.dist-info/WHEEL
mxlengine-0.3.5.dist-info/entry_points.txt
mxlengine-0.3.5.dist-info/RECORD
