Metadata-Version: 2.4
Name: mxlengine
Version: 0.3.5
Summary: MLX Omni Server is a server that provides OpenAI-compatible APIs using Apple's MLX framework.
Project-URL: Repository, https://github.com/madroidmaq/mlx-omni-server
Author-email: madroid <madroidmaq@gmail.com>
License-Expression: MIT
Keywords: agi,ai,aigc,mlx,openai,server,stt,tts
Classifier: Development Status :: 4 - Beta
Classifier: Intended Audience :: Developers
Classifier: Operating System :: OS Independent
Classifier: Programming Language :: Python :: 3.11
Requires-Python: <3.12,>=3.11
Requires-Dist: aiohttp<4,>=3.11.11
Requires-Dist: diffusionkit<0.6,>=0.5.1
Requires-Dist: f5-tts-mlx<0.3,>=0.2.5
Requires-Dist: fastapi<0.116,>=0.115.4
Requires-Dist: huggingface-hub<0.30,>=0.29.1
Requires-Dist: mlx-lm<0.23,>=0.22.4
Requires-Dist: mlx-whisper<0.5,>=0.4.1
Requires-Dist: numba>=0.57.0
Requires-Dist: openai==1.66.3
Requires-Dist: outlines<0.2,>=0.1.11
Requires-Dist: pydantic<3,>=2.9.2
Requires-Dist: python-multipart<0.0.21,>=0.0.20
Requires-Dist: rich>=13.9.4
Requires-Dist: sse-starlette<3,>=2.1.3
Requires-Dist: uvicorn<0.35,>=0.34.0
